rbg2_distributions
