Metadata-Version: 1.0
Name: rbg2-distributions
Version: 0.2
Summary: Gaussian distributions
Home-page: UNKNOWN
Author: HyunSuk O
Author-email: oh_hyunseok@hotmail.com
License: UNKNOWN
Platform: UNKNOWN
